turnvoice/__init__.py
turnvoice/core/__init__.py
turnvoice/core/cli.py
turnvoice/core/cut.py
turnvoice/core/diarize.py
turnvoice/core/download.py
turnvoice/core/fragtokenizer.py
turnvoice/core/prepare.py
turnvoice/core/processing.py
turnvoice/core/prompt.py
turnvoice/core/render.py
turnvoice/core/silence.py
turnvoice/core/silent_audio.wav
turnvoice/core/stretch.py
turnvoice/core/synthesis.py
turnvoice/core/transcribe.py
turnvoice/core/translate.py
turnvoice/core/turnvoice.py
turnvoice/core/verify.py
turnvoice/core/word.py
turnvoice/tests/__init__.py
turnvoice/tests/tests.py
turnvoice/tests/audio/stripsilence_test1.wav
turnvoice/tests/audio/stripsilence_test2.wav
turnvoice/tests/audio/synthesis_verify.wav
turnvoice/tests/audio/testaudio.wav
TurnVoice-0.0.65.dist-info/METADATA
TurnVoice-0.0.65.dist-info/WHEEL
TurnVoice-0.0.65.dist-info/entry_points.txt
TurnVoice-0.0.65.dist-info/top_level.txt
TurnVoice-0.0.65.dist-info/RECORD
