Metadata-Version: 2.1
Name: TurnVoice
Version: 0.0.65
Summary: Replaces and translates voices in youtube videos
Home-page: https://github.com/KoljaB/TurnVoice
Author: Kolja Beigel
Author-email: kolja.beigel@web.de
Keywords: replace,voice,youtube,video,audio,voice,synthesis,sentence-segmentation,TTS-engine,audio-playback,stream-player,sentence-fragment,audio-feedback,interactive,python
Classifier: Programming Language :: Python :: 3
Classifier: License :: OSI Approved :: MIT License
Classifier: Operating System :: OS Independent
Requires-Python: >=3.6
Requires-Dist: moviepy ==1.0.3
Requires-Dist: yt-dlp ==2023.11.16
Requires-Dist: faster-whisper ==0.10.0
Requires-Dist: stable-ts ==2.13.7
Requires-Dist: realtimetts ==0.3.41
Requires-Dist: textdistance ==4.6.0
Requires-Dist: soundfile ==0.12.1
Requires-Dist: pyannote.audio ==3.1.1
Requires-Dist: deep-translator ==1.11.4
Requires-Dist: instructor ==0.4.2
Requires-Dist: demucs ==4.0.1
